funlib/geometry/__init__.py
funlib/geometry/coordinate.py
funlib/geometry/freezable.py
funlib/geometry/py.typed
funlib/geometry/roi.py
funlib.geometry-0.3.0.dist-info/LICENSE
funlib.geometry-0.3.0.dist-info/METADATA
funlib.geometry-0.3.0.dist-info/WHEEL
funlib.geometry-0.3.0.dist-info/top_level.txt
funlib.geometry-0.3.0.dist-info/RECORD
